java2cpp/Java2Cpp.py
java2cpp/__init__.py
java2cpp-0.0.2.dist-info/METADATA
java2cpp-0.0.2.dist-info/WHEEL
java2cpp-0.0.2.dist-info/top_level.txt
java2cpp-0.0.2.dist-info/RECORD
