Metadata-Version: 2.1
Name: java2cpp
Version: 0.0.2
Summary: Java to C++ language translator
Home-page: https://github.com/Ethosa/java2cpp
Author: Ethosa
Author-email: social.ethosa@gmail.com
License: LGPLv3
Project-URL: Github, https://github.com/Ethosa/java2cpp
Project-URL: Documentation, https://github.com/Ethosa/java2cpp
Keywords: java to c++ language translator ethosa
Platform: UNKNOWN
Classifier: Development Status :: 3 - Alpha
Classifier: Programming Language :: Python :: 3
Classifier: Programming Language :: Python :: 3.4
Classifier: Programming Language :: Python :: 3.5
Classifier: Programming Language :: Python :: 3.6
Classifier: Programming Language :: Python :: 3.7
Classifier: License :: OSI Approved :: GNU Lesser General Public License v3 (LGPLv3)
Classifier: Operating System :: OS Independent
Requires-Python: >=3
Requires-Dist: retranslator
